eda_viz/exception.py
eda_viz/viz.py
eda_viz-0.0.3.dist-info/METADATA
eda_viz-0.0.3.dist-info/WHEEL
eda_viz-0.0.3.dist-info/top_level.txt
eda_viz-0.0.3.dist-info/RECORD
