Metadata-Version: 2.1
Name: eda-viz
Version: 0.0.3
Summary: Light-weight Python EDA and Visualization Library for Data Scientists
Home-page: https://github.com/ajaymaity/eda-viz
Author: Ajay Maity
Author-email: eda.viz.py@gmail.com
License: MIT
Platform: UNKNOWN
Classifier: License :: OSI Approved :: MIT License
Classifier: Programming Language :: Python :: 3
Classifier: Programming Language :: Python :: 3.6
Requires-Dist: matplotlib (==3.0.3)
Requires-Dist: pandas (==0.24.2)
Requires-Dist: seaborn (==0.9.0)
